example_publish_pypi_medium/__init__.py
example_publish_pypi_medium/example/__init__.py
example_publish_pypi_medium/example/custom_sklearn.py
mitali_package-1.2.dist-info/METADATA
mitali_package-1.2.dist-info/WHEEL
mitali_package-1.2.dist-info/top_level.txt
mitali_package-1.2.dist-info/RECORD
